odoo10_addon_project_timesheet_currency-10.0.1.0.0-py2.7-nspkg.pth
odoo/addons/project_timesheet_currency/README.rst
odoo/addons/project_timesheet_currency/__init__.py
odoo/addons/project_timesheet_currency/__manifest__.py
odoo/addons/project_timesheet_currency/models/__init__.py
odoo/addons/project_timesheet_currency/models/analytic.py
odoo/addons/project_timesheet_currency/security/analytic_security.xml
odoo/addons/project_timesheet_currency/security/project_security.xml
odoo/addons/project_timesheet_currency/security/record_rules.yml
odoo/addons/project_timesheet_currency/static/description/icon.png
odoo/addons/project_timesheet_currency/tests/__init__.py
odoo/addons/project_timesheet_currency/tests/test_multicurrency_timesheet.py
odoo10_addon_project_timesheet_currency-10.0.1.0.0.dist-info/DESCRIPTION.rst
odoo10_addon_project_timesheet_currency-10.0.1.0.0.dist-info/METADATA
odoo10_addon_project_timesheet_currency-10.0.1.0.0.dist-info/RECORD
odoo10_addon_project_timesheet_currency-10.0.1.0.0.dist-info/WHEEL
odoo10_addon_project_timesheet_currency-10.0.1.0.0.dist-info/metadata.json
odoo10_addon_project_timesheet_currency-10.0.1.0.0.dist-info/namespace_packages.txt
odoo10_addon_project_timesheet_currency-10.0.1.0.0.dist-info/top_level.txt
